Ammeter.py
Ammeterp.py
CCCS.py
CCVS.py
DCCurrent.py
DCVoltage.py
Diode.py
DiodeBridge.py
DiodeZener.py
IDEPyAMS.py
PyAMS.py
Resistor.py
SinCurrent.py
SinCurrentr.py
SinVoltage.py
SymbolEditor.py
VCCS.py
VCVS.py
Voltmeter.py
Voltmeterp.py
__init__.py
appcir.py
apptest.py
armijo.py
data_rc.py
dialogs.py
mainwindow.py
newton.py
option.py
saveData.py
signalType.py
simu.py
standardFunction.py
svg.py
test.py
demo/Kirchhoff/Current Divider.pac
demo/Kirchhoff/KCL.pac
demo/Kirchhoff/KVL.pac
demo/Kirchhoff/Voltage Divider.pac
demo/Kirchhoff/Wheatstone Bridge.pac
demo/Oscillations/Half Wave Rectifier.pac
demo/Oscillations/Multi wave Rectifier.pac
demo/Oscillations/Sinusoidal Waveforms.pac
pv.pyams.egg-info/PKG-INFO
pv.pyams.egg-info/SOURCES.txt
pv.pyams.egg-info/dependency_links.txt
pv.pyams.egg-info/requires.txt
pv.pyams.egg-info/top_level.txt
symbols/basic/CCCS.sym
symbols/basic/CCVS.sym
symbols/basic/Resistor.sym
symbols/basic/VCCS.sym
symbols/basic/VCVS.sym
symbols/multimeter/Ammeter.sym
symbols/multimeter/Ammeterp.sym
symbols/multimeter/Voltmeter.sym
symbols/multimeter/Voltmeterp.sym
symbols/semiconductor/Diode.sym
symbols/semiconductor/DiodeBridge.sym
symbols/semiconductor/DiodeZener.sym
symbols/source/DCCurrent.sym
symbols/source/DCVoltage.sym
symbols/source/SinCurrent.sym
symbols/source/SinVoltage.sym
pv.pyams-0.1.0.0.dist-info/LICENSE
pv.pyams-0.1.0.0.dist-info/METADATA
pv.pyams-0.1.0.0.dist-info/WHEEL
pv.pyams-0.1.0.0.dist-info/top_level.txt
pv.pyams-0.1.0.0.dist-info/RECORD
