Metadata-Version: 2.1
Name: pv.pyams
Version: 0.1.0.0
Summary: PyCir: Python for Simulate Electronic Circuit 
Home-page: https://pv.pyams.org
Author: d.fathi
License: UNKNOWN
Keywords: Creating new symbols ,CAD System,Simulation circuit,PyAMS
Platform: UNKNOWN
Classifier: Programming Language :: Python :: 3
Classifier: License :: OSI Approved :: MIT License
Classifier: Operating System :: OS Independent
Requires-Python: >=3.0
License-File: LICENSE
Requires-Dist: PyQt5
Requires-Dist: PyQtWebEngine
